TickTickAPI/__init__.py
TickTickAPI/tick.py
tests/__init__.py
tests/conftest.py
tests/tests.py
TickTickAPI-1.1.dist-info/METADATA
TickTickAPI-1.1.dist-info/WHEEL
TickTickAPI-1.1.dist-info/top_level.txt
TickTickAPI-1.1.dist-info/RECORD
