Metadata-Version: 2.1
Name: TickTickAPI
Version: 1.1
Summary: UNKNOWN
Home-page: https://gitwork.ru/results/practice-3k/2021/2018-4-02-aku.git
Author: Akulinushkin Oleg
Author-email: oleg.akulinishkin.01@mail.ru
License: UNKNOWN
Platform: UNKNOWN
Requires-Python: >=3.8
Requires-Dist: requests (==2.25.1)
